{
    "Variant1": "Crosstrek AWD 2.0L",
    "Variant2": "Crosstrek AWD 2.0R",
    "Variant3": "Crosstrek AWD 2.0S",
    "Variant4": "Crosstrek AWD Hybrid L",
    "Variant5": "Crosstrek AWD Hybrid S",

    "PC800": "SUBARU DARWIN, 0828",
    "PC2000": "SUBARU SYDNEY CITY, 2018",
    "PC2250": "CENTRAL COAST SUBARU, 2250",
    "PC2264": "CROSSROADS SUBARU, 2285",
    "PC2311": "MUSWELLBROOK SUBARU, 2333",
    "PC2361": "SUBARU TAMWORTH, 2340",
    "PC2500": "TYNAN SUBARU ALBION PARK, 2527",
    "PC2640": "BAKER SUBARU, 2640",
    "PC2620": "CAPITAL SUBARU, 2609",
    "PC2606": "SUBARU CANBERRA, 2606",
    "PC3000": "SUBARU DOCKLANDS, 3008",
    "PC3024": "SUBARU WERRIBEE, 3030",
    "PC3063": "SUBARU ESSENDON, 3041",
    "PC3630": "KEN MUSTON SUBARU, 3630",
    "PC4000": "CITY SUBARU NEWSTEAD, 4006",
    "PC4700": "ROCKHAMPTON SUBARU, 4700",
    "PC5000": "JARVIS SUBARU, 5000",
    "PC5606": "PORT LINCOLN SUBARU, 5606",
    "PC6000": "PERTH CITY SUBARU, 6100",
    "PC6330": "ALBANY SUBARU, 6330",
    "PC7000": "SUBARU HOBART, 7000",
    
    "MPC800": "Darwin City, 0800",
    "MPC2000": "Barangaroo, 2000",
    "MPC2250": "Bucketty, 2250",
    "MPC2264": "Balcolyn, 2264",
    "MPC2311": "Allynbrook, 2311",
    "MPC2361": "Ashford, 2361",
    "MPC2500": "Coniston, 2500",
    "MPC2640": "Albury, 2640",
    "MPC2620": "Beard, 2620",
    "MPC2606": "Chifley, 2606",
    "MPC3000": "Melbourne, 3000",
    "MPC3024": "Fieldstone, 3024",
    "MPC3063": "Oaklands Junction, 3063",
    "MPC3630": "Caniambo, 3630",
    "MPC4000": "Brisbane Adelaide Street, 4000",
    "MPC4700": "Allenstown, 4700",
    "MPC5000": "Adelaide, 5000",
    "MPC5606": "Port Lincoln, 5606",
    "MPC6000": "City Delivery Centre, 6000",
    "MPC6330": "Albany, 6330",
    "MPC7000": "Glebe, 7000",

    "PC800CrosstrekAWD20L": "$39,682",
    "PC800CrosstrekAWD20R": "$43,287",
    "PC800CrosstrekAWD20S": "$46,377",
    "PC800CrosstrekAWDHybridL": "$43,390",
    "PC800CrosstrekAWDHybridS": "$50,085",

    "PC2000CrosstrekAWD20L": "$39,553",
    "PC2000CrosstrekAWD20R": "$43,158",
    "PC2000CrosstrekAWD20S": "$46,248",
    "PC2000CrosstrekAWDHybridL": "$43,448",
    "PC2000CrosstrekAWDHybridS": "$50,195",

    "PC2250CrosstrekAWD20L": "$39,423",
    "PC2250CrosstrekAWD20R": "$43,028",
    "PC2250CrosstrekAWD20S": "$46,118",
    "PC2250CrosstrekAWDHybridL": "$43,318",
    "PC2250CrosstrekAWDHybridS": "$50,065",

    "PC2264CrosstrekAWD20L": "$39,011",
    "PC2264CrosstrekAWD20R": "$42,616",
    "PC2264CrosstrekAWD20S": "$45,706",
    "PC2264CrosstrekAWDHybridL": "$42,906",
    "PC2264CrosstrekAWDHybridS": "$49,645",

    "PC2311CrosstrekAWD20L": "$39,006",
    "PC2311CrosstrekAWD20R": "$42,611",
    "PC2311CrosstrekAWD20S": "$45,701",
    "PC2311CrosstrekAWDHybridL": "$42,901",
    "PC2311CrosstrekAWDHybridS": "$49,640",

    "PC2361CrosstrekAWD20L": "$39,212",
    "PC2361CrosstrekAWD20R": "$42,817",
    "PC2361CrosstrekAWD20S": "$45,907",
    "PC2361CrosstrekAWDHybridL": "$43,107",
    "PC2361CrosstrekAWDHybridS": "$49,850",

    "PC2500CrosstrekAWD20L": "$39,519",
    "PC2500CrosstrekAWD20R": "$43,124",
    "PC2500CrosstrekAWD20S": "$46,214",
    "PC2500CrosstrekAWDHybridL": "$43,414",
    "PC2500CrosstrekAWDHybridS": "$50,161",

    "PC2640CrosstrekAWD20L": "$38,908",
    "PC2640CrosstrekAWD20R": "$42,513",
    "PC2640CrosstrekAWD20S": "$45,603",
    "PC2640CrosstrekAWDHybridL": "$42,803",
    "PC2640CrosstrekAWDHybridS": "$49,540",

    "PC2620CrosstrekAWD20L": "$39,315",
    "PC2620CrosstrekAWD20R": "$42,920",
    "PC2620CrosstrekAWD20S": "$46,010",
    "PC2620CrosstrekAWDHybridL": "$43,210",
    "PC2620CrosstrekAWDHybridS": "$49,955",

    "PC2606CrosstrekAWD20L": "$38,832",
    "PC2606CrosstrekAWD20R": "$42,367",
    "PC2606CrosstrekAWD20S": "$45,397",
    "PC2606CrosstrekAWDHybridL": "$42,663",
    "PC2606CrosstrekAWDHybridS": "$49,253",
    
    "PC3000CrosstrekAWD20L": "$39,991",
    "PC3000CrosstrekAWD20R": "$43,634",
    "PC3000CrosstrekAWD20S": "$46,760",
    "PC3000CrosstrekAWDHybridL": "$43,742",
    "PC3000CrosstrekAWDHybridS": "$50,511",

    "PC3024CrosstrekAWD20L": "$39,935",
    "PC3024CrosstrekAWD20R": "$43,578",
    "PC3024CrosstrekAWD20S": "$46,704",
    "PC3024CrosstrekAWDHybridL": "$43,686",
    "PC3024CrosstrekAWDHybridS": "$50,455",

    "PC3063CrosstrekAWD20L": "$39,869",
    "PC3063CrosstrekAWD20R": "$43,512",
    "PC3063CrosstrekAWD20S": "$46,638",
    "PC3063CrosstrekAWDHybridL": "$43,620",
    "PC3063CrosstrekAWDHybridS": "$50,389",

    "PC3630CrosstrekAWD20L": "$39,429",
    "PC3630CrosstrekAWD20R": "$43,080",
    "PC3630CrosstrekAWD20S": "$46,206",
    "PC3630CrosstrekAWDHybridL": "$43,180",
    "PC3630CrosstrekAWDHybridS": "$49,957",

    "PC4000CrosstrekAWD20L": "$39,162",
    "PC4000CrosstrekAWD20R": "$42,767",
    "PC4000CrosstrekAWD20S": "$45,857",
    "PC4000CrosstrekAWDHybridL": "$42,484",
    "PC4000CrosstrekAWDHybridS": "$49,114",

    "PC4700CrosstrekAWD20L": "$39,162",
    "PC4700CrosstrekAWD20R": "$42,767",
    "PC4700CrosstrekAWD20S": "$45,857",
    "PC4700CrosstrekAWDHybridL": "$42,484",
    "PC4700CrosstrekAWDHybridS": "$49,114",

    "PC5000CrosstrekAWD20L": "$39,274",
    "PC5000CrosstrekAWD20R": "$42,914",
    "PC5000CrosstrekAWD20S": "$46,034",
    "PC5000CrosstrekAWDHybridL": "$43,018",
    "PC5000CrosstrekAWDHybridS": "$49,778",

    "PC5606CrosstrekAWD20L": "$38,914",
    "PC5606CrosstrekAWD20R": "$42,554",
    "PC5606CrosstrekAWD20S": "$45,674",
    "PC5606CrosstrekAWDHybridL": "$42,658",
    "PC5606CrosstrekAWDHybridS": "$49,418",

    "PC6000CrosstrekAWD20L": "$39,866",     "MPC6000CrosstrekAWD20L": "$39,866",
    "PC6000CrosstrekAWD20R": "$43,714",
    "PC6000CrosstrekAWD20S": "$47,044",
    "PC6000CrosstrekAWDHybridL": "$43,853",     "MPC6000CrosstrekAWDHybridL": "$43,854",
    "PC6000CrosstrekAWDHybridS": "$51,102",

    "PC6330CrosstrekAWD20L": "$39,866",     "MPC6330CrosstrekAWD20L": "$39,866",
    "PC6330CrosstrekAWD20R": "$43,714",
    "PC6330CrosstrekAWD20S": "$47,044",
    "PC6330CrosstrekAWDHybridL": "$43,853",  "MPC6330CrosstrekAWDHybridL": "$43,854",
    "PC6330CrosstrekAWDHybridS": "$51,102",
    
    "PC7000CrosstrekAWD20L": "$39,036",
    "PC7000CrosstrekAWD20R": "$42,872",
    "PC7000CrosstrekAWD20S": "$45,992",
    "PC7000CrosstrekAWDHybridL": "$42,976",
    "PC7000CrosstrekAWDHybridS": "$49,736"
  }
  
