{
    "Variant1": "Outback AWD",
    "Variant2": "Outback AWD Sport",
    "Variant3": "Outback AWD Touring",
    "Variant4": "Outback AWD Sport XT",
    "Variant5": "Outback AWD Touring XT",

    "MPVariant1": "Subaru Outback AWD",
    "MPVariant2": "Subaru Outback AWD Sport",
    "MPVariant3": "Subaru Outback AWD Touring",
    "MPVariant4": "Subaru Outback AWD Sport XT",
    "MPVariant5": "Subaru Outback AWD Touring XT",

    "PC800": "SUBARU DARWIN, 0828",
    "PC2000": "SUBARU SYDNEY CITY, 2018",
    "PC2250": "CENTRAL COAST SUBARU, 2250",
    "PC2264": "CROSSROADS SUBARU, 2285",
    "PC2311": "MUSWELLBROOK SUBARU, 2333",
    "PC2361": "SUBARU TAMWORTH, 2340",
    "PC2500": "TYNAN SUBARU ALBION PARK, 2527",
    "PC2640": "BAKER SUBARU, 2640",
    "PC2620": "CAPITAL SUBARU, 2609",
    "PC2606": "SUBARU CANBERRA, 2606",
    "PC3000": "SUBARU DOCKLANDS, 3008",
    "PC3024": "SUBARU WERRIBEE, 3030",
    "PC3063": "SUBARU ESSENDON, 3041",
    "PC3630": "KEN MUSTON SUBARU, 3630",
    "PC4000": "CITY SUBARU NEWSTEAD, 4006",
    "PC4700": "ROCKHAMPTON SUBARU, 4700",
    "PC5000": "JARVIS SUBARU, 5000",
    "PC5606": "PORT LINCOLN SUBARU, 5606",
    "PC6000": "PERTH CITY SUBARU, 6100",
    "PC6330": "ALBANY SUBARU, 6330",
    "PC7000": "SUBARU HOBART, 7000",
    
    "MPC800": "Darwin City, 0800",
    "MPC2000": "Barangaroo, 2000",
    "MPC2250": "Bucketty, 2250",
    "MPC2264": "Balcolyn, 2264",
    "MPC2311": "Allynbrook, 2311",
    "MPC2361": "Ashford, 2361",
    "MPC2500": "Coniston, 2500",
    "MPC2640": "Albury, 2640",
    "MPC2620": "Beard, 2620",
    "MPC2606": "Chifley, 2606",
    "MPC3000": "Melbourne, 3000",
    "MPC3024": "Fieldstone, 3024",
    "MPC3063": "Oaklands Junction, 3063",
    "MPC3630": "Caniambo, 3630",
    "MPC4000": "Brisbane Adelaide Street, 4000",
    "MPC4700": "Allenstown, 4700",
    "MPC5000": "Adelaide, 5000",
    "MPC5606": "Port Lincoln, 5606",
    "MPC6000": "City Delivery Centre, 6000",
    "MPC6330": "Albany, 6330",
    "MPC7000": "Glebe, 7000",


    "PC800OutbackAWD": "$48,643",
    "PC800OutbackSport": "$53,278",
    "PC800OutbackTouring": "$57,192",
    "PC800OutbackSportXT": "$58,428",
    "PC800OutbackTouringXT": "$62,342",

    "PC2000OutbackAWD": "$48,725",
    "PC2000OutbackSport": "$53,450",
    "PC2000OutbackTouring": "$57,440",
    "PC2000OutbackSportXT": "$58,700",
    "PC2000OutbackTouringXT": "$62,690",

    "PC2250OutbackAWD": "$48,595",
    "PC2250OutbackSport": "$53,320",
    "PC2250OutbackTouring": "$57,310",
    "PC2250OutbackSportXT": "$58,570",
    "PC2250OutbackTouringXT": "$62,560",

    "PC2264OutbackAWD": "$48,175",
    "PC2264OutbackSport": "$52,900",
    "PC2264OutbackTouring": "$56,890",
    "PC2264OutbackSportXT": "$58,150",
    "PC2264OutbackTouringXT": "$62,140",

    "PC2311OutbackAWD": "$48,170",
    "PC2311OutbackSport": "$52,895",
    "PC2311OutbackTouring": "$56,885",
    "PC2311OutbackSportXT": "$58,145",
    "PC2311OutbackTouringXT": "$62,135",

    "PC2361OutbackAWD": "$48,380",
    "PC2361OutbackSport": "$53,105",
    "PC2361OutbackTouring": "$57,095",
    "PC2361OutbackSportXT": "$58,355",
    "PC2361OutbackTouringXT": "$62,345",

    "PC2500OutbackAWD": "$48,691",
    "PC2500OutbackSport": "$53,416",
    "PC2500OutbackTouring": "$57,406",
    "PC2500OutbackSportXT": "$58,666",
    "PC2500OutbackTouringXT": "$62,656",

    "PC2640OutbackAWD": "$48,070",
    "PC2640OutbackSport": "$52,795",
    "PC2640OutbackTouring": "$56,785",
    "PC2640OutbackSportXT": "$58,045",
    "PC2640OutbackTouringXT": "$62,035",

    "PC2620OutbackAWD": "$48,485",
    "PC2620OutbackSport": "$53,210",
    "PC2620OutbackTouring": "$57,200",
    "PC2620OutbackSportXT": "$58,460",
    "PC2620OutbackTouringXT": "$62,450",

    "PC2606OutbackAWD": "$47,825",
    "PC2606OutbackSport": "$52,415",
    "PC2606OutbackTouring": "$56,291",
    "PC2606OutbackSportXT": "$58,767",
    "PC2606OutbackTouringXT": "$62,761",
    
    "PC3000OutbackAWD": "$49,052",
    "PC3000OutbackSport": "$53,745",
    "PC3000OutbackTouring": "$57,705",
    "PC3000OutbackSportXT": "$58,955",
    "PC3000OutbackTouringXT": "$62,915",

    "PC3024OutbackAWD": "$48,996",
    "PC3024OutbackSport": "$53,689",
    "PC3024OutbackTouring": "$57,649",
    "PC3024OutbackSportXT": "$58,899",
    "PC3024OutbackTouringXT": "$62,859",

    "PC3063OutbackAWD": "$48,930",
    "PC3063OutbackSport": "$53,623",
    "PC3063OutbackTouring": "$57,583",
    "PC3063OutbackSportXT": "$58,833",
    "PC3063OutbackTouringXT": "$62,793",

    "PC3630OutbackAWD": "$48,499",
    "PC3630OutbackSport": "$53,183",
    "PC3630OutbackTouring": "$57,143",
    "PC3630OutbackSportXT": "$58,393",
    "PC3630OutbackTouringXT": "$62,353",

    "PC4000OutbackAWD": "$48,123",
    "PC4000OutbackSport": "$52,758",
    "PC4000OutbackTouring": "$56,672",
    "PC4000OutbackSportXT": "$57,908",
    "PC4000OutbackTouringXT": "$61,822",

    "PC4700OutbackAWD": "$48,123",
    "PC4700OutbackSport": "$52,758",
    "PC4700OutbackTouring": "$56,672",
    "PC4700OutbackSportXT": "$57,908",
    "PC4700OutbackTouringXT": "$61,822",

    "PC5000OutbackAWD": "$48,322",
    "PC5000OutbackSport": "$53,002",
    "PC5000OutbackTouring": "$56,954",
    "PC5000OutbackSportXT": "$58,202",
    "PC5000OutbackTouringXT": "$62,154",

    "PC5606OutbackAWD": "$47,962",
    "PC5606OutbackSport": "$52,642",
    "PC5606OutbackTouring": "$56,594",
    "PC5606OutbackSportXT": "$57,842",
    "PC5606OutbackTouringXT": "$61,794",

    "PC6000OutbackAWD": "$49,556",     "MPPC6000OutbackAWD": "$49,556",
    "PC6000OutbackSport": "$54,634",
    "PC6000OutbackTouring": "$58,811",
    "PC6000OutbackSportXT": "$60,089",
    "PC6000OutbackTouringXT": "$64,162",

    "PC6330OutbackAWD": "$49,556", "MPPC6330OutbackAWD": "$49,556",
    "PC6330OutbackSport": "$54,634",
    "PC6330OutbackTouring": "$58,811",
    "PC6330OutbackSportXT": "$60,089",
    "PC6330OutbackTouringXT": "$64,162",

    "PC7000OutbackAWD": "$48,280",
    "PC7000OutbackSport": "$52,960",
    "PC7000OutbackTouring": "$56,912",
    "PC7000OutbackSportXT": "$58,160",
    "PC7000OutbackTouringXT": "$62,112"

  }
  
